lisp_utils/__init__.py
lisp_utils/configuration.py
lisp_utils/database.py
lisp_utils-0.6.1.dist-info/LICENSE
lisp_utils-0.6.1.dist-info/METADATA
lisp_utils-0.6.1.dist-info/WHEEL
lisp_utils-0.6.1.dist-info/top_level.txt
lisp_utils-0.6.1.dist-info/RECORD
