Metadata-Version: 2.1
Name: lisp-utils
Version: 0.6.1
Summary: This package contains some Linkspirit classes such as Database, Configuration.
Home-page: https://gitlab.linkspirit.it/linkspirit/python-lisp-utils.git
Author: Linkspirit Team
Author-email: tecnici@linkspirit.it
License: UNKNOWN
Platform: UNKNOWN
Classifier: Programming Language :: Python :: 3
Classifier: Operating System :: OS Independent
Requires-Python: >=3
License-File: LICENSE
Requires-Dist: psycopg2-binary
